fontdump/core.py
fontdump/cli.py
fontdump/__init__.py
fontdump-1.3.0.dist-info/DESCRIPTION.rst
fontdump-1.3.0.dist-info/RECORD
fontdump-1.3.0.dist-info/METADATA
fontdump-1.3.0.dist-info/top_level.txt
fontdump-1.3.0.dist-info/metadata.json
fontdump-1.3.0.dist-info/entry_points.txt
fontdump-1.3.0.dist-info/WHEEL
