Metadata-Version: 2.0
Name: fontdump
Version: 1.3.0
Summary: A cli tool to dump the CSS and different formats offonts for Google Fonts
Home-page: https://github.com/glasslion/fontdump
Author: Leonardo Zhou
Author-email: glasslion@gmail.com
License: MIT
Keywords: font webfont
Platform: UNKNOWN
Classifier: Development Status :: 5 - Production/Stable
Classifier: Intended Audience :: Developers
Classifier: Topic :: Software Development :: Build Tools
Classifier: License :: OSI Approved :: MIT License
Classifier: Programming Language :: Python :: 2
Classifier: Programming Language :: Python :: 2.6
Classifier: Programming Language :: Python :: 2.7
Requires-Dist: requests
Requires-Dist: cssutils
Requires-Dist: docopt
